{
  "step_id": "root",
  "question": "What are you experiencing?",
  "options": [
    {
      "label": "Cough, Cold & Flu",
      "value": "Cough, Cold & Flu",
      "next_step": {
        "step_id": "level_2",
        "question": "How severe is your cough?",
        "options": [
          {
            "label": "Cough",
            "value": "Cough",
            "next_step": {
              "step_id": "level_3",
              "question": "Do you prefer to swallow, chew, or drink your medicine?",
              "options": [
                {
                  "label": "Tablets",
                  "value": "Tablets",
                  "is_final": true
                },
                {
                  "label": "Lozenges",
                  "value": "Lozenges",
                  "is_final": true
                },
                {
                  "label": "Sachets",
                  "value": "Sachets",
                  "is_final": true
                },
                {
                  "label": "Cream/Ointment",
                  "value": "Cream/Ointment",
                  "is_final": true
                },
                {
                  "label": "Capsules",
                  "value": "Capsules",
                  "is_final": true
                },
                {
                  "label": "Syrup/Liquid",
                  "value": "Syrup/Liquid",
                  "is_final": true
                },
                {
                  "label": "Drops",
                  "value": "Drops",
                  "is_final": true
                }
              ]
            }
          },
          {
            "label": "Sore Throat",
            "value": "Sore Throat",
            "next_step": {
              "step_id": "level_3",
              "question": "Do you prefer to swallow, suck on, drink, or spray your medicine?",
              "options": [
                {
                  "label": "Tablets",
                  "value": "Tablets",
                  "is_final": true
                },
                {
                  "label": "Lozenges",
                  "value": "Lozenges",
                  "is_final": true
                },
                {
                  "label": "Tea",
                  "value": "Tea",
                  "is_final": true
                },
                {
                  "label": "Syrup/Liquid",
                  "value": "Syrup/Liquid",
                  "is_final": true
                },
                {
                  "label": "Drops",
                  "value": "Drops",
                  "is_final": true
                },
                {
                  "label": "Spray",
                  "value": "Spray",
                  "is_final": true
                },
                {
                  "label": "Gel",
                  "value": "Gel",
                  "is_final": true
                }
              ]
            }
          },
          {
            "label": "Sinus Pain",
            "value": "Sinus Pain",
            "next_step": {
              "step_id": "level_3",
              "question": "Do you prefer to swallow or drink your medicine?",
              "options": [
                {
                  "label": "Tablets",
                  "value": "Tablets",
                  "is_final": true
                },
                {
                  "label": "Syrup/Liquid",
                  "value": "Syrup/Liquid",
                  "is_final": true
                }
              ]
            }
          },
          {
            "label": "Cold",
            "value": "Cold",
            "next_step": {
              "step_id": "level_3",
              "question": "Do you prefer to swallow, drink, or apply your medicine?",
              "options": [
                {
                  "label": "Tablets",
                  "value": "Tablets",
                  "is_final": true
                },
                {
                  "label": "Sachets",
                  "value": "Sachets",
                  "is_final": true
                },
                {
                  "label": "Cream/Ointment",
                  "value": "Cream/Ointment",
                  "is_final": true
                },
                {
                  "label": "Syrup/Liquid",
                  "value": "Syrup/Liquid",
                  "is_final": true
                },
                {
                  "label": "Spray",
                  "value": "Spray",
                  "is_final": true
                }
              ]
            }
          },
          {
            "label": "Nasal Congestion",
            "value": "Nasal Congestion",
            "next_step": {
              "step_id": "level_3",
              "question": "Do you prefer to inhale, swallow, drink, or apply your medicine?",
              "options": [
                {
                  "label": "Inhalant Oil",
                  "value": "Inhalant Oil",
                  "is_final": true
                },
                {
                  "label": "Sachets",
                  "value": "Sachets",
                  "is_final": true
                },
                {
                  "label": "Cream/Ointment",
                  "value": "Cream/Ointment",
                  "is_final": true
                },
                {
                  "label": "Capsules",
                  "value": "Capsules",
                  "is_final": true
                },
                {
                  "label": "Syrup/Liquid",
                  "value": "Syrup/Liquid",
                  "is_final": true
                },
                {
                  "label": "Oil",
                  "value": "Oil",
                  "is_final": true
                },
                {
                  "label": "Drops",
                  "value": "Drops",
                  "is_final": true
                },
                {
                  "label": "Spray",
                  "value": "Spray",
                  "is_final": true
                },
                {
                  "label": "Gel",
                  "value": "Gel",
                  "is_final": true
                }
              ]
            }
          },
          {
            "label": "Flu",
            "value": "Flu",
            "next_step": {
              "step_id": "level_3",
              "question": "Do you prefer to swallow, suck on, drink, or apply your medicine?",
              "options": [
                {
                  "label": "Tablets",
                  "value": "Tablets",
                  "is_final": true
                },
                {
                  "label": "Lozenges",
                  "value": "Lozenges",
                  "is_final": true
                },
                {
                  "label": "Sachets",
                  "value": "Sachets",
                  "is_final": true
                },
                {
                  "label": "Capsules",
                  "value": "Capsules",
                  "is_final": true
                },
                {
                  "label": "Syrup/Liquid",
                  "value": "Syrup/Liquid",
                  "is_final": true
                },
                {
                  "label": "Oil",
                  "value": "Oil",
                  "is_final": true
                }
              ]
            }
          },
          {
            "label": "Nasal Congestion/Irritation",
            "value": "Nasal Congestion/Irritation",
            "next_step": {
              "step_id": "level_3",
              "question": "Do you prefer to apply your medicine as a gel?",
              "options": [
                {
                  "label": "Gel",
                  "value": "Gel",
                  "is_final": true
                }
              ]
            }
          }
        ]
      }
    },
    {
      "label": "Pain & Fever",
      "value": "Pain & Fever",
      "next_step": {
        "step_id": "level_2",
        "question": "Where is the pain located?",
        "options": [
          {
            "label": "Muscle Pain",
            "value": "Muscle Pain",
            "next_step": {
              "step_id": "level_3",
              "question": "Do you prefer to swallow, chew, drink, or apply your medicine?",
              "options": [
                {
                  "label": "Tablets",
                  "value": "Tablets",
                  "is_final": true
                },
                {
                  "label": "Granules",
                  "value": "Granules",
                  "is_final": true
                },
                {
                  "label": "Sheet",
                  "value": "Sheet",
                  "is_final": true
                },
                {
                  "label": "Sachets",
                  "value": "Sachets",
                  "is_final": true
                },
                {
                  "label": "Suppositories",
                  "value": "Suppositories",
                  "is_final": true
                },
                {
                  "label": "Cream/Ointment",
                  "value": "Cream/Ointment",
                  "is_final": true
                },
                {
                  "label": "Capsules",
                  "value": "Capsules",
                  "is_final": true
                },
                {
                  "label": "Syrup/Liquid",
                  "value": "Syrup/Liquid",
                  "is_final": true
                },
                {
                  "label": "Oil",
                  "value": "Oil",
                  "is_final": true
                },
                {
                  "label": "Plasters",
                  "value": "Plasters",
                  "is_final": true
                },
                {
                  "label": "Drops",
                  "value": "Drops",
                  "is_final": true
                },
                {
                  "label": "Spray",
                  "value": "Spray",
                  "is_final": true
                },
                {
                  "label": "Gel",
                  "value": "Gel",
                  "is_final": true
                }
              ]
            }
          },
          {
            "label": "Feverish Conditions",
            "value": "Feverish Conditions",
            "next_step": {
              "step_id": "level_3",
              "question": "Do you prefer to swallow, insert, drink, or apply your medicine?",
              "options": [
                {
                  "label": "Tablets",
                  "value": "Tablets",
                  "is_final": true
                },
                {
                  "label": "Sheet",
                  "value": "Sheet",
                  "is_final": true
                },
                {
                  "label": "Suppositories",
                  "value": "Suppositories",
                  "is_final": true
                },
                {
                  "label": "Cream/Ointment",
                  "value": "Cream/Ointment",
                  "is_final": true
                },
                {
                  "label": "Syrup/Liquid",
                  "value": "Syrup/Liquid",
                  "is_final": true
                },
                {
                  "label": "Kids/Infant",
                  "value": "Kids/Infant",
                  "is_final": true
                }
              ]
            }
          },
          {
            "label": "Headache",
            "value": "Headache",
            "next_step": {
              "step_id": "level_3",
              "question": "Do you prefer to swallow, chew, drink, or spray your medicine?",
              "options": [
                {
                  "label": "Tablets",
                  "value": "Tablets",
                  "is_final": true
                },
                {
                  "label": "Sachets",
                  "value": "Sachets",
                  "is_final": true
                },
                {
                  "label": "Cream/Ointment",
                  "value": "Cream/Ointment",
                  "is_final": true
                },
                {
                  "label": "Capsules",
                  "value": "Capsules",
                  "is_final": true
                },
                {
                  "label": "Oil",
                  "value": "Oil",
                  "is_final": true
                },
                {
                  "label": "Spray",
                  "value": "Spray",
                  "is_final": true
                }
              ]
            }
          },
          {
            "label": "Joint Pain",
            "value": "Joint Pain",
            "next_step": {
              "step_id": "level_3",
              "question": "Do you prefer to swallow, chew, or apply your medicine?",
              "options": [
                {
                  "label": "Tablets",
                  "value": "Tablets",
                  "is_final": true
                },
                {
                  "label": "Sachets",
                  "value": "Sachets",
                  "is_final": true
                },
                {
                  "label": "Cream/Ointment",
                  "value": "Cream/Ointment",
                  "is_final": true
                },
                {
                  "label": "Gel",
                  "value": "Gel",
                  "is_final": true
                }
              ]
            }
          },
          {
            "label": "Sinus Pain",
            "value": "Sinus Pain",
            "next_step": {
              "step_id": "level_3",
              "question": "Do you prefer to swallow your medicine?",
              "options": [
                {
                  "label": "Tablets",
                  "value": "Tablets",
                  "is_final": true
                }
              ]
            }
          },
          {
            "label": "Back Pain",
            "value": "Back Pain",
            "next_step": {
              "step_id": "level_3",
              "question": "Do you prefer to apply a plaster or cream?",
              "options": [
                {
                  "label": "Plasters",
                  "value": "Plasters",
                  "is_final": true
                },
                {
                  "label": "Tablets",
                  "value": "Tablets",
                  "is_final": true
                },
                {
                  "label": "Cream/Ointment",
                  "value": "Cream/Ointment",
                  "is_final": true
                }
              ]
            }
          },
          {
            "label": "Sore Throat",
            "value": "Sore Throat",
            "next_step": {
              "step_id": "level_3",
              "question": "Do you prefer to spray your medicine?",
              "options": [
                {
                  "label": "Spray",
                  "value": "Spray",
                  "is_final": true
                }
              ]
            }
          },
          {
            "label": "Period Pain",
            "value": "Period Pain",
            "next_step": {
              "step_id": "level_3",
              "question": "Do you prefer to swallow or chew your medicine?",
              "options": [
                {
                  "label": "Tablets",
                  "value": "Tablets",
                  "is_final": true
                },
                {
                  "label": "Sachets",
                  "value": "Sachets",
                  "is_final": true
                }
              ]
            }
          },
          {
            "label": "Toothache",
            "value": "Toothache",
            "next_step": {
              "step_id": "level_3",
              "question": "Do you prefer to drink or apply your medicine?",
              "options": [
                {
                  "label": "Syrup/Liquid",
                  "value": "Syrup/Liquid",
                  "is_final": true
                },
                {
                  "label": "Gel",
                  "value": "Gel",
                  "is_final": true
                }
              ]
            }
          }
        ]
      }
    },
    {
      "label": "Digestive Health",
      "value": "Digestive Health",
      "next_step": {
        "step_id": "level_2",
        "question": "When did your digestive issues start?",
        "options": [
          {
            "label": "Acid Reflux/Heartburn",
            "value": "Acid Reflux/Heartburn",
            "next_step": {
              "step_id": "level_3",
              "question": "Do you prefer to swallow, chew, drink, or take a suspension?",
              "options": [
                {
                  "label": "Tablets",
                  "value": "Tablets",
                  "is_final": true
                },
                {
                  "label": "Sachets",
                  "value": "Sachets",
                  "is_final": true
                },
                {
                  "label": "Suspension",
                  "value": "Suspension",
                  "is_final": true
                },
                {
                  "label": "Capsules",
                  "value": "Capsules",
                  "is_final": true
                },
                {
                  "label": "Syrup/Liquid",
                  "value": "Syrup/Liquid",
                  "is_final": true
                },
                {
                  "label": "Gel",
                  "value": "Gel",
                  "is_final": true
                }
              ]
            }
          },
          {
            "label": "Gas/Bloating",
            "value": "Gas/Bloating",
            "next_step": {
              "step_id": "level_3",
              "question": "Do you prefer to swallow or drink your medicine?",
              "options": [
                {
                  "label": "Tablets",
                  "value": "Tablets",
                  "is_final": true
                },
                {
                  "label": "Syrup/Liquid",
                  "value": "Syrup/Liquid",
                  "is_final": true
                },
                {
                  "label": "Capsules",
                  "value": "Capsules",
                  "is_final": true
                }
              ]
            }
          },
          {
            "label": "Constipation",
            "value": "Constipation",
            "next_step": {
              "step_id": "level_3",
              "question": "Do you prefer to swallow, chew, drink, insert, or take a suspension?",
              "options": [
                {
                  "label": "Tablets",
                  "value": "Tablets",
                  "is_final": true
                },
                {
                  "label": "Sachets",
                  "value": "Sachets",
                  "is_final": true
                },
                {
                  "label": "Suppositories",
                  "value": "Suppositories",
                  "is_final": true
                },
                {
                  "label": "Tea",
                  "value": "Tea",
                  "is_final": true
                },
                {
                  "label": "Suspension",
                  "value": "Suspension",
                  "is_final": true
                },
                {
                  "label": "Capsules",
                  "value": "Capsules",
                  "is_final": true
                },
                {
                  "label": "Syrup/Liquid",
                  "value": "Syrup/Liquid",
                  "is_final": true
                },
                {
                  "label": "Oil",
                  "value": "Oil",
                  "is_final": true
                }
              ]
            }
          },
          {
            "label": "Diarrhea",
            "value": "Diarrhea",
            "next_step": {
              "step_id": "level_3",
              "question": "Do you prefer to swallow, chew, drink, or take a suspension?",
              "options": [
                {
                  "label": "Tablets",
                  "value": "Tablets",
                  "is_final": true
                },
                {
                  "label": "Sachets",
                  "value": "Sachets",
                  "is_final": true
                },
                {
                  "label": "Soluble Tablets",
                  "value": "Soluble Tablets",
                  "is_final": true
                },
                {
                  "label": "Suspension",
                  "value": "Suspension",
                  "is_final": true
                },
                {
                  "label": "Capsules",
                  "value": "Capsules",
                  "is_final": true
                },
                {
                  "label": "Syrup/Liquid",
                  "value": "Syrup/Liquid",
                  "is_final": true
                }
              ]
            }
          },
          {
            "label": "Irritable Bowel Syndrome (IBS)",
            "value": "Irritable Bowel Syndrome (IBS)",
            "next_step": {
              "step_id": "level_3",
              "question": "Do you prefer to swallow your medicine?",
              "options": [
                {
                  "label": "Tablets",
                  "value": "Tablets",
                  "is_final": true
                },
                {
                  "label": "Capsules",
                  "value": "Capsules",
                  "is_final": true
                }
              ]
            }
          },
          {
            "label": "Other",
            "value": "Other",
            "next_step": {
              "step_id": "level_3",
              "question": "Do you prefer to swallow your medicine?",
              "options": [
                {
                  "label": "Capsules",
                  "value": "Capsules",
                  "is_final": true
                }
              ]
            }
          },
          {
            "label": "Nausea/Vomiting",
            "value": "Nausea/Vomiting",
            "next_step": {
              "step_id": "level_3",
              "question": "Do you prefer to swallow, drink, or take a suspension?",
              "options": [
                {
                  "label": "Tablets",
                  "value": "Tablets",
                  "is_final": true
                },
                {
                  "label": "Syrup/Liquid",
                  "value": "Syrup/Liquid",
                  "is_final": true
                },
                {
                  "label": "Suspension",
                  "value": "Suspension",
                  "is_final": true
                },
                {
                  "label": "Capsules",
                  "value": "Capsules",
                  "is_final": true
                }
              ]
            }
          },
          {
            "label": "Cramps",
            "value": "Cramps",
            "next_step": {
              "step_id": "level_3",
              "question": "Do you prefer to swallow or drink your medicine?",
              "options": [
                {
                  "label": "Tablets",
                  "value": "Tablets",
                  "is_final": true
                },
                {
                  "label": "Syrup/Liquid",
                  "value": "Syrup/Liquid",
                  "is_final": true
                }
              ]
            }
          }
        ]
      }
    },
    {
      "label": "Allergies",
      "value": "Allergies",
      "next_step": {
        "step_id": "level_2",
        "question": "What seems to trigger your allergies?",
        "options": [
          {
            "label": "Skin Allergies",
            "value": "Skin Allergies",
            "next_step": {
              "step_id": "level_3",
              "question": "Do you prefer to swallow or drink your medicine?",
              "options": [
                {
                  "label": "Tablets",
                  "value": "Tablets",
                  "is_final": true
                },
                {
                  "label": "Syrup/Liquid",
                  "value": "Syrup/Liquid",
                  "is_final": true
                },
                {
                  "label": "Drops",
                  "value": "Drops",
                  "is_final": true
                }
              ]
            }
          },
          {
            "label": "Nasal Allergies",
            "value": "Nasal Allergies",
            "next_step": {
              "step_id": "level_3",
              "question": "Do you prefer to swallow, drink, or spray your medicine?",
              "options": [
                {
                  "label": "Tablets",
                  "value": "Tablets",
                  "is_final": true
                },
                {
                  "label": "Syrup/Liquid",
                  "value": "Syrup/Liquid",
                  "is_final": true
                },
                {
                  "label": "Spray",
                  "value": "Spray",
                  "is_final": true
                }
              ]
            }
          },
          {
            "label": "Seasonal Allergies",
            "value": "Seasonal Allergies",
            "next_step": {
              "step_id": "level_3",
              "question": "Do you prefer to swallow, drink, or spray your medicine?",
              "options": [
                {
                  "label": "Tablets",
                  "value": "Tablets",
                  "is_final": true
                },
                {
                  "label": "Syrup/Liquid",
                  "value": "Syrup/Liquid",
                  "is_final": true
                },
                {
                  "label": "Spray",
                  "value": "Spray",
                  "is_final": true
                },
                {
                  "label": "Drops",
                  "value": "Drops",
                  "is_final": true
                }
              ]
            }
          },
          {
            "label": "Allergies",
            "value": "Allergies",
            "next_step": {
              "step_id": "level_3",
              "question": "Do you prefer to drink your medicine?",
              "options": [
                {
                  "label": "Drops",
                  "value": "Drops",
                  "is_final": true
                },
                {
                  "label": "Syrup/Liquid",
                  "value": "Syrup/Liquid",
                  "is_final": true
                }
              ]
            }
          }
        ]
      }
    },
    {
      "label": "Eye Care",
      "value": "Eye Care",
      "next_step": {
        "step_id": "level_2",
        "question": "Is there any discharge from your eyes?",
        "options": [
          {
            "label": "Dry Eyes",
            "value": "Dry Eyes",
            "next_step": {
              "step_id": "level_3",
              "question": "Do you prefer to apply an ointment or eye drops?",
              "options": [
                {
                  "label": "Ointment/Cream",
                  "value": "Ointment/Cream",
                  "is_final": true
                },
                {
                  "label": "Eye Gel",
                  "value": "Eye Gel",
                  "is_final": true
                },
                {
                  "label": "Cream/Ointment",
                  "value": "Cream/Ointment",
                  "is_final": true
                },
                {
                  "label": "Eye Drops",
                  "value": "Eye Drops",
                  "is_final": true
                }
              ]
            }
          },
          {
            "label": "Eye Irritation/Redness",
            "value": "Eye Irritation/Redness",
            "next_step": {
              "step_id": "level_3",
              "question": "Do you prefer to swallow, apply a solution, or use eye drops?",
              "options": [
                {
                  "label": "Tablets",
                  "value": "Tablets",
                  "is_final": true
                },
                {
                  "label": "Solution",
                  "value": "Solution",
                  "is_final": true
                },
                {
                  "label": "Cream/Ointment",
                  "value": "Cream/Ointment",
                  "is_final": true
                },
                {
                  "label": "Other",
                  "value": "Other",
                  "is_final": true
                },
                {
                  "label": "Eye Drops",
                  "value": "Eye Drops",
                  "is_final": true
                },
                {
                  "label": "Contact Lenses",
                  "value": "Contact Lenses",
                  "is_final": true
                },
                {
                  "label": "Wipes",
                  "value": "Wipes",
                  "is_final": true
                },
                {
                  "label": "Drops",
                  "value": "Drops",
                  "is_final": true
                }
              ]
            }
          },
          {
            "label": "Allergies",
            "value": "Allergies",
            "next_step": {
              "step_id": "level_3",
              "question": "Do you prefer to use eye drops?",
              "options": [
                {
                  "label": "Eye Drops",
                  "value": "Eye Drops",
                  "is_final": true
                }
              ]
            }
          },
          {
            "label": "Contact Lens Related Issues",
            "value": "Contact Lens Related Issues",
            "next_step": {
              "step_id": "level_3",
              "question": "Do you prefer to use a solution or contact lenses?",
              "options": [
                {
                  "label": "Solution",
                  "value": "Solution",
                  "is_final": true
                },
                {
                  "label": "Contact Lenses",
                  "value": "Contact Lenses",
                  "is_final": true
                },
                {
                  "label": "Ophthalmic Solution",
                  "value": "Ophthalmic Solution",
                  "is_final": true
                },
                {
                  "label": "Wipes",
                  "value": "Wipes",
                  "is_final": true
                }
              ]
            }
          },
          {
            "label": "Eye Infections",
            "value": "Eye Infections",
            "next_step": {
              "step_id": "level_3",
              "question": "Do you prefer to apply a cream or eye drops?",
              "options": [
                {
                  "label": "Cream/Ointment",
                  "value": "Cream/Ointment",
                  "is_final": true
                },
                {
                  "label": "Eye Drops",
                  "value": "Eye Drops",
                  "is_final": true
                },
                {
                  "label": "Eye Ointment",
                  "value": "Eye Ointment",
                  "is_final": true
                }
              ]
            }
          },
          {
            "label": "Other",
            "value": "Other",
            "next_step": {
              "step_id": "level_3",
              "question": "Do you prefer to use an ophthalmic solution?",
              "options": [
                {
                  "label": "Other",
                  "value": "Other",
                  "is_final": true
                },
                {
                  "label": "Ophthalmic Solution",
                  "value": "Ophthalmic Solution",
                  "is_final": true
                }
              ]
            }
          },
          {
            "label": "Tired Eyes",
            "value": "Tired Eyes",
            "next_step": {
              "step_id": "level_3",
              "question": "Do you prefer to use eye drops or contact lenses?",
              "options": [
                {
                  "label": "Eye Drops",
                  "value": "Eye Drops",
                  "is_final": true
                },
                {
                  "label": "Contact Lenses",
                  "value": "Contact Lenses",
                  "is_final": true
                }
              ]
            }
          },
          {
            "label": "Eye Allergies",
            "value": "Eye Allergies",
            "next_step": {
              "step_id": "level_3",
              "question": "Do you prefer to apply a cream or eye drops?",
              "options": [
                {
                  "label": "Cream/Ointment",
                  "value": "Cream/Ointment",
                  "is_final": true
                },
                {
                  "label": "Eye Drops",
                  "value": "Eye Drops",
                  "is_final": true
                }
              ]
            }
          }
        ]
      }
    },
    {
      "label": "First Aid",
      "value": "First Aid",
      "next_step": {
        "step_id": "level_2",
        "question": "How did the injury occur?",
        "options": [
          {
            "label": "Wound Care",
            "value": "Wound Care",
            "next_step": {
              "step_id": "level_3",
              "question": "Do you prefer to gargle, apply an ointment, or use a plaster?",
              "options": [
                {
                  "label": "Mouthwash/Gargle",
                  "value": "Mouthwash/Gargle",
                  "is_final": true
                },
                {
                  "label": "Ointment",
                  "value": "Ointment",
                  "is_final": true
                },
                {
                  "label": "Plasters",
                  "value": "Plasters",
                  "is_final": true
                },
                {
                  "label": "Sheet",
                  "value": "Sheet",
                  "is_final": true
                },
                {
                  "label": "Powder",
                  "value": "Powder",
                  "is_final": true
                },
                {
                  "label": "Tablets",
                  "value": "Tablets",
                  "is_final": true
                },
                {
                  "label": "Solution",
                  "value": "Solution",
                  "is_final": true
                },
                {
                  "label": "Cream/Ointment",
                  "value": "Cream/Ointment",
                  "is_final": true
                },
                {
                  "label": "Bandages & Dressings",
                  "value": "Bandages & Dressings",
                  "is_final": true
                },
                {
                  "label": "General Supplies",
                  "value": "General Supplies",
                  "is_final": true
                },
                {
                  "label": "Spray",
                  "value": "Spray",
                  "is_final": true
                },
                {
                  "label": "Gel",
                  "value": "Gel",
                  "is_final": true
                }
              ]
            }
          },
          {
            "label": "Bandages & Dressings",
            "value": "Bandages & Dressings",
            "next_step": {
              "step_id": "level_3",
              "question": "Do you prefer to apply a solution or spray?",
              "options": [
                {
                  "label": "Solution",
                  "value": "Solution",
                  "is_final": true
                },
                {
                  "label": "Spray",
                  "value": "Spray",
                  "is_final": true
                },
                {
                  "label": "Bandages & Dressings",
                  "value": "Bandages & Dressings",
                  "is_final": true
                }
              ]
            }
          },
          {
            "label": "Antiseptics",
            "value": "Antiseptics",
            "next_step": {
              "step_id": "level_3",
              "question": "Do you prefer to apply a solution, powder, or spray?",
              "options": [
                {
                  "label": "Solution",
                  "value": "Solution",
                  "is_final": true
                },
                {
                  "label": "Powder",
                  "value": "Powder",
                  "is_final": true
                },
                {
                  "label": "Syrup/Liquid",
                  "value": "Syrup/Liquid",
                  "is_final": true
                },
                {
                  "label": "Spray",
                  "value": "Spray",
                  "is_final": true
                }
              ]
            }
          },
          {
            "label": "Oral Hygiene/Care",
            "value": "Oral Hygiene/Care",
            "next_step": {
              "step_id": "level_3",
              "question": "Do you prefer to gargle, apply a cream, or use a spray?",
              "options": [
                {
                  "label": "Mouthwash/Gargle",
                  "value": "Mouthwash/Gargle",
                  "is_final": true
                },
                {
                  "label": "Cream/Ointment/Gel",
                  "value": "Cream/Ointment/Gel",
                  "is_final": true
                },
                {
                  "label": "Solution",
                  "value": "Solution",
                  "is_final": true
                },
                {
                  "label": "Oil",
                  "value": "Oil",
                  "is_final": true
                },
                {
                  "label": "General Supplies",
                  "value": "General Supplies",
                  "is_final": true
                },
                {
                  "label": "Spray",
                  "value": "Spray",
                  "is_final": true
                },
                {
                  "label": "Gel",
                  "value": "Gel",
                  "is_final": true
                }
              ]
            }
          },
          {
            "label": "Pain Relief (Topical)",
            "value": "Pain Relief (Topical)",
            "next_step": {
              "step_id": "level_3",
              "question": "Do you prefer to apply a sheet, cream, or plaster?",
              "options": [
                {
                  "label": "Sheet",
                  "value": "Sheet",
                  "is_final": true
                },
                {
                  "label": "Cream/Ointment",
                  "value": "Cream/Ointment",
                  "is_final": true
                },
                {
                  "label": "Oil",
                  "value": "Oil",
                  "is_final": true
                },
                {
                  "label": "Plasters",
                  "value": "Plasters",
                  "is_final": true
                },
                {
                  "label": "Spray",
                  "value": "Spray",
                  "is_final": true
                },
                {
                  "label": "Gel",
                  "value": "Gel",
                  "is_final": true
                }
              ]
            }
          },
          {
            "label": "General Supplies",
            "value": "General Supplies",
            "next_step": {
              "step_id": "level_3",
              "question": "Do you prefer to apply a cream or spray?",
              "options": [
                {
                  "label": "Comb",
                  "value": "Comb",
                  "is_final": true
                },
                {
                  "label": "Cream/Ointment",
                  "value": "Cream/Ointment",
                  "is_final": true
                },
                {
                  "label": "Other",
                  "value": "Other",
                  "is_final": true
                },
                {
                  "label": "General Supplies",
                  "value": "General Supplies",
                  "is_final": true
                },
                {
                  "label": "Spray",
                  "value": "Spray",
                  "is_final": true
                }
              ]
            }
          },
          {
            "label": "Muscle Pain",
            "value": "Muscle Pain",
            "next_step": {
              "step_id": "level_3",
              "question": "Do you need general first aid supplies?",
              "options": [
                {
                  "label": "General Supplies",
                  "value": "General Supplies",
                  "is_final": true
                }
              ]
            }
          },
          {
            "label": "Hot/Cold Therapy",
            "value": "Hot/Cold Therapy",
            "next_step": {
              "step_id": "level_3",
              "question": "Do you prefer to apply a solution, sheet, or gel?",
              "options": [
                {
                  "label": "Solution",
                  "value": "Solution",
                  "is_final": true
                },
                {
                  "label": "Sheet",
                  "value": "Sheet",
                  "is_final": true
                },
                {
                  "label": "Oil",
                  "value": "Oil",
                  "is_final": true
                },
                {
                  "label": "Gel",
                  "value": "Gel",
                  "is_final": true
                }
              ]
            }
          },
          {
            "label": "First Aid",
            "value": "First Aid",
            "next_step": {
              "step_id": "level_3",
              "question": "Do you need general first aid supplies or a spray?",
              "options": [
                {
                  "label": "General Supplies",
                  "value": "General Supplies",
                  "is_final": true
                },
                {
                  "label": "Spray",
                  "value": "Spray",
                  "is_final": true
                }
              ]
            }
          },
          {
            "label": "Eye Care",
            "value": "Eye Care",
            "next_step": {
              "step_id": "level_3",
              "question": "Do you need general eye care supplies?",
              "options": [
                {
                  "label": "General Supplies",
                  "value": "General Supplies",
                  "is_final": true
                }
              ]
            }
          },
          {
            "label": "Insect Repellent",
            "value": "Insect Repellent",
            "next_step": {
              "step_id": "level_3",
              "question": "Do you prefer to apply a cream or spray?",
              "options": [
                {
                  "label": "Other",
                  "value": "Other",
                  "is_final": true
                },
                {
                  "label": "Cream/Ointment",
                  "value": "Cream/Ointment",
                  "is_final": true
                },
                {
                  "label": "Spray",
                  "value": "Spray",
                  "is_final": true
                }
              ]
            }
          },
          {
            "label": "Ear Care",
            "value": "Ear Care",
            "next_step": {
              "step_id": "level_3",
              "question": "Do you prefer to drink or spray your medicine?",
              "options": [
                {
                  "label": "Syrup/Liquid",
                  "value": "Syrup/Liquid",
                  "is_final": true
                },
                {
                  "label": "Drops",
                  "value": "Drops",
                  "is_final": true
                },
                {
                  "label": "Spray",
                  "value": "Spray",
                  "is_final": true
                },
                {
                  "label": "Gel",
                  "value": "Gel",
                  "is_final": true
                }
              ]
            }
          },
          {
            "label": "Scar Management",
            "value": "Scar Management",
            "next_step": {
              "step_id": "level_3",
              "question": "Do you prefer to apply a sheet or gel?",
              "options": [
                {
                  "label": "Sheet",
                  "value": "Sheet",
                  "is_final": true
                },
                {
                  "label": "Gel",
                  "value": "Gel",
                  "is_final": true
                }
              ]
            }
          },
          {
            "label": "Feverish Conditions",
            "value": "Feverish Conditions",
            "next_step": {
              "step_id": "level_3",
              "question": "Do you prefer to apply a sheet?",
              "options": [
                {
                  "label": "Sheet",
                  "value": "Sheet",
                  "is_final": true
                }
              ]
            }
          },
          {
            "label": "Other",
            "value": "Other",
            "next_step": {
              "step_id": "level_3",
              "question": "Do you prefer to use a conditioner, shampoo, or spray?",
              "options": [
                {
                  "label": "Conditioner",
                  "value": "Conditioner",
                  "is_final": true
                },
                {
                  "label": "Shampoo",
                  "value": "Shampoo",
                  "is_final": true
                },
                {
                  "label": "Spray",
                  "value": "Spray",
                  "is_final": true
                }
              ]
            }
          },
          {
            "label": "Nasal Congestion/Irritation",
            "value": "Nasal Congestion/Irritation",
            "next_step": {
              "step_id": "level_3",
              "question": "Do you prefer to use a spray?",
              "options": [
                {
                  "label": "Spray",
                  "value": "Spray",
                  "is_final": true
                }
              ]
            }
          },
          {
            "label": "Skin Irritation/Reaction",
            "value": "Skin Irritation/Reaction",
            "next_step": {
              "step_id": "level_3",
              "question": "Do you prefer to drink your medicine?",
              "options": [
                {
                  "label": "Drops",
                  "value": "Drops",
                  "is_final": true
                }
              ]
            }
          },
          {
            "label": "Hemorrhoid Symptoms",
            "value": "Hemorrhoid Symptoms",
            "next_step": {
              "step_id": "level_3",
              "question": "Do you prefer to use suppositories?",
              "options": [
                {
                  "label": "Suppositories",
                  "value": "Suppositories",
                  "is_final": true
                }
              ]
            }
          }
        ]
      }
    },
    {
      "label": "Vitamins & Supplements",
      "value": "Vitamins & Supplements",
      "next_step": {
        "step_id": "level_2",
        "question": "What are you hoping to improve with vitamins or supplements?",
        "options": [
          {
            "label": "Other",
            "value": "Other",
            "next_step": {
              "step_id": "level_3",
              "question": "Do you prefer to swallow, chew, drink, or use drops?",
              "options": [
                {
                  "label": "Tablets",
                  "value": "Tablets",
                  "is_final": true
                },
                {
                  "label": "Sachets",
                  "value": "Sachets",
                  "is_final": true
                },
                {
                  "label": "Pellets",
                  "value": "Pellets",
                  "is_final": true
                },
                {
                  "label": "Capsules",
                  "value": "Capsules",
                  "is_final": true
                },
                {
                  "label": "Homeopathic Remedies",
                  "value": "Homeopathic Remedies",
                  "is_final": true
                },
                {
                  "label": "Syrup/Liquid",
                  "value": "Syrup/Liquid",
                  "is_final": true
                },
                {
                  "label": "Kids/Infant",
                  "value": "Kids/Infant",
                  "is_final": true
                },
                {
                  "label": "Drops",
                  "value": "Drops",
                  "is_final": true
                }
              ]
            }
          },
          {
            "label": "Skin Irritation/Reaction",
            "value": "Skin Irritation/Reaction",
            "next_step": {
              "step_id": "level_3",
              "question": "Do you prefer to suck on a lozenge or use drops?",
              "options": [
                {
                  "label": "Drops",
                  "value": "Drops",
                  "is_final": true
                },
                {
                  "label": "Lozenges",
                  "value": "Lozenges",
                  "is_final": true
                },
                {
                  "label": "Homeopathic Remedies",
                  "value": "Homeopathic Remedies",
                  "is_final": true
                }
              ]
            }
          },
          {
            "label": "Nausea/Vomiting",
            "value": "Nausea/Vomiting",
            "next_step": {
              "step_id": "level_3",
              "question": "Do you prefer to use drops?",
              "options": [
                {
                  "label": "Drops",
                  "value": "Drops",
                  "is_final": true
                }
              ]
            }
          },
          {
            "label": "Herbal Supplements",
            "value": "Herbal Supplements",
            "next_step": {
              "step_id": "level_3",
              "question": "Do you prefer to swallow, drink, or use drops?",
              "options": [
                {
                  "label": "Tablets",
                  "value": "Tablets",
                  "is_final": true
                },
                {
                  "label": "Oral Solution",
                  "value": "Oral Solution",
                  "is_final": true
                },
                {
                  "label": "Capsules",
                  "value": "Capsules",
                  "is_final": true
                },
                {
                  "label": "Syrup/Liquid",
                  "value": "Syrup/Liquid",
                  "is_final": true
                },
                {
                  "label": "Drops",
                  "value": "Drops",
                  "is_final": true
                }
              ]
            }
          },
          {
            "label": "Homeopathic Remedies",
            "value": "Homeopathic Remedies",
            "next_step": {
              "step_id": "level_3",
              "question": "Do you prefer to swallow, suck on, drink, or use drops?",
              "options": [
                {
                  "label": "Tablets",
                  "value": "Tablets",
                  "is_final": true
                },
                {
                  "label": "Drops",
                  "value": "Drops",
                  "is_final": true
                },
                {
                  "label": "Syrup/Liquid",
                  "value": "Syrup/Liquid",
                  "is_final": true
                },
                {
                  "label": "Lozenges",
                  "value": "Lozenges",
                  "is_final": true
                }
              ]
            }
          },
          {
            "label": "Irritable Bowel Syndrome (IBS)",
            "value": "Irritable Bowel Syndrome (IBS)",
            "next_step": {
              "step_id": "level_3",
              "question": "Do you prefer to chew your medicine?",
              "options": [
                {
                  "label": "Sachets",
                  "value": "Sachets",
                  "is_final": true
                }
              ]
            }
          },
          {
            "label": "Minerals",
            "value": "Minerals",
            "next_step": {
              "step_id": "level_3",
              "question": "Do you prefer to swallow, chew, or drink your medicine?",
              "options": [
                {
                  "label": "Tablets",
                  "value": "Tablets",
                  "is_final": true
                },
                {
                  "label": "Sachets",
                  "value": "Sachets",
                  "is_final": true
                },
                {
                  "label": "Syrup/Liquid",
                  "value": "Syrup/Liquid",
                  "is_final": true
                }
              ]
            }
          },
          {
            "label": "Digestive Health",
            "value": "Digestive Health",
            "next_step": {
              "step_id": "level_3",
              "question": "Do you prefer to swallow or drink your medicine?",
              "options": [
                {
                  "label": "Tablets",
                  "value": "Tablets",
                  "is_final": true
                },
                {
                  "label": "Syrup/Liquid",
                  "value": "Syrup/Liquid",
                  "is_final": true
                },
                {
                  "label": "Homeopathic Remedies",
                  "value": "Homeopathic Remedies",
                  "is_final": true
                }
              ]
            }
          },
          {
            "label": "Joint Pain",
            "value": "Joint Pain",
            "next_step": {
              "step_id": "level_3",
              "question": "Do you prefer to use drops?",
              "options": [
                {
                  "label": "Drops",
                  "value": "Drops",
                  "is_final": true
                }
              ]
            }
          },
          {
            "label": "Hemorrhoid Symptoms",
            "value": "Hemorrhoid Symptoms",
            "next_step": {
              "step_id": "level_3",
              "question": "Do you prefer to use drops?",
              "options": [
                {
                  "label": "Drops",
                  "value": "Drops",
                  "is_final": true
                },
                {
                  "label": "Homeopathic Remedies",
                  "value": "Homeopathic Remedies",
                  "is_final": true
                }
              ]
            }
          },
          {
            "label": "Neurological Symptoms",
            "value": "Neurological Symptoms",
            "next_step": {
              "step_id": "level_3",
              "question": "Do you prefer to swallow, drink, or use drops?",
              "options": [
                {
                  "label": "Tablets",
                  "value": "Tablets",
                  "is_final": true
                },
                {
                  "label": "Drops",
                  "value": "Drops",
                  "is_final": true
                },
                {
                  "label": "Syrup/Liquid",
                  "value": "Syrup/Liquid",
                  "is_final": true
                },
                {
                  "label": "Homeopathic Remedies",
                  "value": "Homeopathic Remedies",
                  "is_final": true
                }
              ]
            }
          },
          {
            "label": "Allergies",
            "value": "Allergies",
            "next_step": {
              "step_id": "level_3",
              "question": "Do you prefer to use drops?",
              "options": [
                {
                  "label": "Drops",
                  "value": "Drops",
                  "is_final": true
                },
                {
                  "label": "Homeopathic Remedies",
                  "value": "Homeopathic Remedies",
                  "is_final": true
                }
              ]
            }
          },
          {
            "label": "Constipation",
            "value": "Constipation",
            "next_step": {
              "step_id": "level_3",
              "question": "Do you prefer to suck on a lozenge?",
              "options": [
                {
                  "label": "Lozenges",
                  "value": "Lozenges",
                  "is_final": true
                },
                {
                  "label": "Homeopathic Remedies",
                  "value": "Homeopathic Remedies",
                  "is_final": true
                }
              ]
            }
          },
          {
            "label": "Cough",
            "value": "Cough",
            "next_step": {
              "step_id": "level_3",
              "question": "Do you prefer to suck on a lozenge?",
              "options": [
                {
                  "label": "Pellets",
                  "value": "Pellets",
                  "is_final": true
                },
                {
                  "label": "Lozenges",
                  "value": "Lozenges",
                  "is_final": true
                },
                {
                  "label": "Homeopathic Remedies",
                  "value": "Homeopathic Remedies",
                  "is_final": true
                }
              ]
            }
          },
          {
            "label": "Muscle Pain",
            "value": "Muscle Pain",
            "next_step": {
              "step_id": "level_3",
              "question": "Do you prefer to swallow, drink, or suck on a lozenge?",
              "options": [
                {
                  "label": "Tablets",
                  "value": "Tablets",
                  "is_final": true
                },
                {
                  "label": "Oral Solution",
                  "value": "Oral Solution",
                  "is_final": true
                },
                {
                  "label": "Lozenges",
                  "value": "Lozenges",
                  "is_final": true
                },
                {
                  "label": "Homeopathic Remedies",
                  "value": "Homeopathic Remedies",
                  "is_final": true
                },
                {
                  "label": "Syrup/Liquid",
                  "value": "Syrup/Liquid",
                  "is_final": true
                }
              ]
            }
          },
          {
            "label": "Skin Care",
            "value": "Skin Care",
            "next_step": {
              "step_id": "level_3",
              "question": "Do you prefer to use homeopathic remedies?",
              "options": [
                {
                  "label": "Homeopathic Remedies",
                  "value": "Homeopathic Remedies",
                  "is_final": true
                }
              ]
            }
          },
          {
            "label": "Headache",
            "value": "Headache",
            "next_step": {
              "step_id": "level_3",
              "question": "Do you prefer to suck on a lozenge?",
              "options": [
                {
                  "label": "Lozenges",
                  "value": "Lozenges",
                  "is_final": true
                }
              ]
            }
          },
          {
            "label": "Eye Care",
            "value": "Eye Care",
            "next_step": {
              "step_id": "level_3",
              "question": "Do you prefer to use homeopathic remedies?",
              "options": [
                {
                  "label": "Homeopathic Remedies",
                  "value": "Homeopathic Remedies",
                  "is_final": true
                }
              ]
            }
          },
          {
            "label": "Cough, Cold & Flu",
            "value": "Cough, Cold & Flu",
            "next_step": {
              "step_id": "level_3",
              "question": "Do you prefer to use pellets?",
              "options": [
                {
                  "label": "Pellets",
                  "value": "Pellets",
                  "is_final": true
                },
                {
                  "label": "Homeopathic Remedies",
                  "value": "Homeopathic Remedies",
                  "is_final": true
                }
              ]
            }
          },
          {
            "label": "Supplements for Children",
            "value": "Supplements for Children",
            "next_step": {
              "step_id": "level_3",
              "question": "Do you prefer to swallow or drink your medicine?",
              "options": [
                {
                  "label": "Sachets",
                  "value": "Sachets",
                  "is_final": true
                },
                {
                  "label": "Tablets",
                  "value": "Tablets",
                  "is_final": true
                },
                {
                  "label": "Oral Solution",
                  "value": "Oral Solution",
                  "is_final": true
                }
              ]
            }
          },
          {
            "label": "Skin Allergies",
            "value": "Skin Allergies",
            "next_step": {
              "step_id": "level_3",
              "question": "Do you prefer to suck on a lozenge?",
              "options": [
                {
                  "label": "Lozenges",
                  "value": "Lozenges",
                  "is_final": true
                }
              ]
            }
          },
          {
            "label": "Sore Throat",
            "value": "Sore Throat",
            "next_step": {
              "step_id": "level_3",
              "question": "Do you prefer to swallow or suck on a lozenge?",
              "options": [
                {
                  "label": "Tablets",
                  "value": "Tablets",
                  "is_final": true
                },
                {
                  "label": "Lozenges",
                  "value": "Lozenges",
                  "is_final": true
                }
              ]
            }
          },
          {
            "label": "Single Vitamins",
            "value": "Single Vitamins",
            "next_step": {
              "step_id": "level_3",
              "question": "Do you prefer to swallow, suck on a lozenge, or get an injection?",
              "options": [
                {
                  "label": "Tablets",
                  "value": "Tablets",
                  "is_final": true
                },
                {
                  "label": "Oral Solution",
                  "value": "Oral Solution",
                  "is_final": true
                },
                {
                  "label": "Injection",
                  "value": "Injection",
                  "is_final": true
                },
                {
                  "label": "Lozenges",
                  "value": "Lozenges",
                  "is_final": true
                }
              ]
            }
          },
          {
            "label": "Feverish Conditions",
            "value": "Feverish Conditions",
            "next_step": {
              "step_id": "level_3",
              "question": "Do you prefer to swallow your medicine?",
              "options": [
                {
                  "label": "Tablets",
                  "value": "Tablets",
                  "is_final": true
                }
              ]
            }
          }
        ]
      }
    },
    {
      "label": "Other",
      "value": "Other",
      "next_step": {
        "step_id": "level_2",
        "question": "Can you describe the symptom in more detail?",
        "options": [
          {
            "label": "Nasal Congestion/Irritation",
            "value": "Nasal Congestion/Irritation",
            "next_step": {
              "step_id": "level_3",
              "question": "Do you prefer to inhale, apply a solution, or use a spray?",
              "options": [
                {
                  "label": "Inhalant Oil",
                  "value": "Inhalant Oil",
                  "is_final": true
                },
                {
                  "label": "Solution",
                  "value": "Solution",
                  "is_final": true
                },
                {
                  "label": "Syrup/Liquid",
                  "value": "Syrup/Liquid",
                  "is_final": true
                },
                {
                  "label": "Spray",
                  "value": "Spray",
                  "is_final": true
                },
                {
                  "label": "Gel",
                  "value": "Gel",
                  "is_final": true
                }
              ]
            }
          },
          {
            "label": "Other",
            "value": "Other",
            "next_step": {
              "step_id": "level_3",
              "question": "Do you prefer to swallow, suck on, chew, drink, or use drops?",
              "options": [
                {
                  "label": "Tablets",
                  "value": "Tablets",
                  "is_final": true
                },
                {
                  "label": "Lozenges",
                  "value": "Lozenges",
                  "is_final": true
                },
                {
                  "label": "Gum",
                  "value": "Gum",
                  "is_final": true
                },
                {
                  "label": "Other",
                  "value": "Other",
                  "is_final": true
                },
                {
                  "label": "Syrup/Liquid",
                  "value": "Syrup/Liquid",
                  "is_final": true
                },
                {
                  "label": "Patches",
                  "value": "Patches",
                  "is_final": true
                },
                {
                  "label": "Drops",
                  "value": "Drops",
                  "is_final": true
                }
              ]
            }
          },
          {
            "label": "Hemorrhoid Symptoms",
            "value": "Hemorrhoid Symptoms",
            "next_step": {
              "step_id": "level_3",
              "question": "Do you prefer to swallow, insert, or apply a cream?",
              "options": [
                {
                  "label": "Tablets",
                  "value": "Tablets",
                  "is_final": true
                },
                {
                  "label": "Suppositories",
                  "value": "Suppositories",
                  "is_final": true
                },
                {
                  "label": "Cream/Ointment",
                  "value": "Cream/Ointment",
                  "is_final": true
                },
                {
                  "label": "Capsules",
                  "value": "Capsules",
                  "is_final": true
                },
                {
                  "label": "Gel",
                  "value": "Gel",
                  "is_final": true
                }
              ]
            }
          },
          {
            "label": "Hormonal Imbalance Symptoms",
            "value": "Hormonal Imbalance Symptoms",
            "next_step": {
              "step_id": "level_3",
              "question": "Do you prefer to swallow, chew, get an injection, or apply a gel?",
              "options": [
                {
                  "label": "Tablets",
                  "value": "Tablets",
                  "is_final": true
                },
                {
                  "label": "Sachets",
                  "value": "Sachets",
                  "is_final": true
                },
                {
                  "label": "Capsules",
                  "value": "Capsules",
                  "is_final": true
                },
                {
                  "label": "Patches",
                  "value": "Patches",
                  "is_final": true
                },
                {
                  "label": "Injection",
                  "value": "Injection",
                  "is_final": true
                },
                {
                  "label": "Gel",
                  "value": "Gel",
                  "is_final": true
                }
              ]
            }
          },
          {
            "label": "Neurological Symptoms",
            "value": "Neurological Symptoms",
            "next_step": {
              "step_id": "level_3",
              "question": "Do you prefer to swallow, drink, or use drops?",
              "options": [
                {
                  "label": "Tablets",
                  "value": "Tablets",
                  "is_final": true
                },
                {
                  "label": "Other",
                  "value": "Other",
                  "is_final": true
                },
                {
                  "label": "Capsules",
                  "value": "Capsules",
                  "is_final": true
                },
                {
                  "label": "Syrup/Liquid",
                  "value": "Syrup/Liquid",
                  "is_final": true
                },
                {
                  "label": "Drops",
                  "value": "Drops",
                  "is_final": true
                },
                {
                  "label": "Spray",
                  "value": "Spray",
                  "is_final": true
                }
              ]
            }
          },
          {
            "label": "Skin Irritation/Reaction",
            "value": "Skin Irritation/Reaction",
            "next_step": {
              "step_id": "level_3",
              "question": "Do you prefer to swallow, drink, or apply a solution?",
              "options": [
                {
                  "label": "Tablets",
                  "value": "Tablets",
                  "is_final": true
                },
                {
                  "label": "Oral Solution",
                  "value": "Oral Solution",
                  "is_final": true
                },
                {
                  "label": "Solution",
                  "value": "Solution",
                  "is_final": true
                },
                {
                  "label": "Capsules",
                  "value": "Capsules",
                  "is_final": true
                },
                {
                  "label": "Syrup/Liquid",
                  "value": "Syrup/Liquid",
                  "is_final": true
                },
                {
                  "label": "Spray",
                  "value": "Spray",
                  "is_final": true
                }
              ]
            }
          },
          {
            "label": "Nausea/Vomiting",
            "value": "Nausea/Vomiting",
            "next_step": {
              "step_id": "level_3",
              "question": "Do you prefer to swallow or chew your medicine?",
              "options": [
                {
                  "label": "Tablets",
                  "value": "Tablets",
                  "is_final": true
                },
                {
                  "label": "Sachets",
                  "value": "Sachets",
                  "is_final": true
                },
                {
                  "label": "Syrup/Liquid",
                  "value": "Syrup/Liquid",
                  "is_final": true
                }
              ]
            }
          },
          {
            "label": "Sore Throat",
            "value": "Sore Throat",
            "next_step": {
              "step_id": "level_3",
              "question": "Do you prefer to swallow your medicine?",
              "options": [
                {
                  "label": "Tablets",
                  "value": "Tablets",
                  "is_final": true
                }
              ]
            }
          }
        ]
      }
    },
    {
      "label": "Skin Care",
      "value": "Skin Care",
      "next_step": {
        "step_id": "level_2",
        "question": "Where on your body is the skin irritation?",
        "options": [
          {
            "label": "Dry/Flaky Skin",
            "value": "Dry/Flaky Skin",
            "next_step": {
              "step_id": "level_3",
              "question": "Do you prefer to apply a solution, cream, or oil?",
              "options": [
                {
                  "label": "Solution",
                  "value": "Solution",
                  "is_final": true
                },
                {
                  "label": "Cream/Ointment",
                  "value": "Cream/Ointment",
                  "is_final": true
                },
                {
                  "label": "Oil",
                  "value": "Oil",
                  "is_final": true
                },
                {
                  "label": "Lotion",
                  "value": "Lotion",
                  "is_final": true
                },
                {
                  "label": "Spray",
                  "value": "Spray",
                  "is_final": true
                },
                {
                  "label": "Gel",
                  "value": "Gel",
                  "is_final": true
                }
              ]
            }
          },
          {
            "label": "Skin Irritation/Reaction",
            "value": "Skin Irritation/Reaction",
            "next_step": {
              "step_id": "level_3",
              "question": "Do you prefer to apply a solution, cream, or lotion?",
              "options": [
                {
                  "label": "Solution",
                  "value": "Solution",
                  "is_final": true
                },
                {
                  "label": "Cream/Ointment",
                  "value": "Cream/Ointment",
                  "is_final": true
                },
                {
                  "label": "Syrup/Liquid",
                  "value": "Syrup/Liquid",
                  "is_final": true
                },
                {
                  "label": "Lotion",
                  "value": "Lotion",
                  "is_final": true
                },
                {
                  "label": "Plasters",
                  "value": "Plasters",
                  "is_final": true
                },
                {
                  "label": "Gel",
                  "value": "Gel",
                  "is_final": true
                }
              ]
            }
          },
          {
            "label": "Scars/Stretch Marks",
            "value": "Scars/Stretch Marks",
            "next_step": {
              "step_id": "level_3",
              "question": "Do you prefer to apply a sheet, cream, or oil?",
              "options": [
                {
                  "label": "Sheet",
                  "value": "Sheet",
                  "is_final": true
                },
                {
                  "label": "Cream/Ointment",
                  "value": "Cream/Ointment",
                  "is_final": true
                },
                {
                  "label": "Oil",
                  "value": "Oil",
                  "is_final": true
                },
                {
                  "label": "Lotion",
                  "value": "Lotion",
                  "is_final": true
                },
                {
                  "label": "Gel",
                  "value": "Gel",
                  "is_final": true
                }
              ]
            }
          },
          {
            "label": "Skin Allergies",
            "value": "Skin Allergies",
            "next_step": {
              "step_id": "level_3",
              "question": "Do you prefer to apply a cream?",
              "options": [
                {
                  "label": "Cream/Ointment",
                  "value": "Cream/Ointment",
                  "is_final": true
                }
              ]
            }
          },
          {
            "label": "Psoriasis",
            "value": "Psoriasis",
            "next_step": {
              "step_id": "level_3",
              "question": "Do you prefer to apply a cream or spray?",
              "options": [
                {
                  "label": "Cream/Ointment",
                  "value": "Cream/Ointment",
                  "is_final": true
                },
                {
                  "label": "Spray",
                  "value": "Spray",
                  "is_final": true
                },
                {
                  "label": "Gel",
                  "value": "Gel",
                  "is_final": true
                },
                {
                  "label": "Lotion",
                  "value": "Lotion",
                  "is_final": true
                }
              ]
            }
          },
          {
            "label": "Eczema/Dermatitis",
            "value": "Eczema/Dermatitis",
            "next_step": {
              "step_id": "level_3",
              "question": "Do you prefer to apply an ointment or cream?",
              "options": [
                {
                  "label": "Ointment",
                  "value": "Ointment",
                  "is_final": true
                },
                {
                  "label": "Cream/Ointment",
                  "value": "Cream/Ointment",
                  "is_final": true
                }
              ]
            }
          },
          {
            "label": "Other",
            "value": "Other",
            "next_step": {
              "step_id": "level_3",
              "question": "Do you prefer to apply a solution, cream, or spray?",
              "options": [
                {
                  "label": "Solution",
                  "value": "Solution",
                  "is_final": true
                },
                {
                  "label": "Cream/Ointment",
                  "value": "Cream/Ointment",
                  "is_final": true
                },
                {
                  "label": "Spray",
                  "value": "Spray",
                  "is_final": true
                },
                {
                  "label": "Gel",
                  "value": "Gel",
                  "is_final": true
                }
              ]
            }
          },
          {
            "label": "Bacterial Infection",
            "value": "Bacterial Infection",
            "next_step": {
              "step_id": "level_3",
              "question": "Do you prefer to swallow or apply a cream?",
              "options": [
                {
                  "label": "Tablets",
                  "value": "Tablets",
                  "is_final": true
                },
                {
                  "label": "Cream/Ointment",
                  "value": "Cream/Ointment",
                  "is_final": true
                },
                {
                  "label": "Ointment",
                  "value": "Ointment",
                  "is_final": true
                },
                {
                  "label": "Cream",
                  "value": "Cream",
                  "is_final": true
                }
              ]
            }
          },
          {
            "label": "Fungal Infection",
            "value": "Fungal Infection",
            "next_step": {
              "step_id": "level_3",
              "question": "Do you prefer to swallow, apply a solution, or use a spray?",
              "options": [
                {
                  "label": "Tablets",
                  "value": "Tablets",
                  "is_final": true
                },
                {
                  "label": "Solution",
                  "value": "Solution",
                  "is_final": true
                },
                {
                  "label": "Cream/Ointment",
                  "value": "Cream/Ointment",
                  "is_final": true
                },
                {
                  "label": "Capsules",
                  "value": "Capsules",
                  "is_final": true
                },
                {
                  "label": "Spray",
                  "value": "Spray",
                  "is_final": true
                }
              ]
            }
          },
          {
            "label": "Acne",
            "value": "Acne",
            "next_step": {
              "step_id": "level_3",
              "question": "Do you prefer to apply a cream or gel?",
              "options": [
                {
                  "label": "Cream/Ointment",
                  "value": "Cream/Ointment",
                  "is_final": true
                },
                {
                  "label": "Gel",
                  "value": "Gel",
                  "is_final": true
                }
              ]
            }
          },
          {
            "label": "Allergic Skin Conditions",
            "value": "Allergic Skin Conditions",
            "next_step": {
              "step_id": "level_3",
              "question": "Do you prefer to apply an ointment or cream?",
              "options": [
                {
                  "label": "Ointment",
                  "value": "Ointment",
                  "is_final": true
                },
                {
                  "label": "Cream",
                  "value": "Cream",
                  "is_final": true
                },
                {
                  "label": "Gel",
                  "value": "Gel",
                  "is_final": true
                }
              ]
            }
          },
          {
            "label": "Muscle Pain",
            "value": "Muscle Pain",
            "next_step": {
              "step_id": "level_3",
              "question": "Do you prefer to apply an oil?",
              "options": [
                {
                  "label": "Oil",
                  "value": "Oil",
                  "is_final": true
                }
              ]
            }
          }
        ]
      }
    },
    {
      "label": "Feminine Care & Contraceptives",
      "value": "Feminine Care & Contraceptives",
      "next_step": {
        "step_id": "level_2",
        "question": "What are your specific concerns regarding feminine care?",
        "options": [
          {
            "label": "Hormonal Imbalance Treatment",
            "value": "Hormonal Imbalance Treatment",
            "next_step": {
              "step_id": "level_3",
              "question": "Do you prefer to swallow your medicine?",
              "options": [
                {
                  "label": "Tablets",
                  "value": "Tablets",
                  "is_final": true
                }
              ]
            }
          },
          {
            "label": "Vaginal Infections",
            "value": "Vaginal Infections",
            "next_step": {
              "step_id": "level_3",
              "question": "Do you prefer to swallow or insert your medicine?",
              "options": [
                {
                  "label": "Tablets",
                  "value": "Tablets",
                  "is_final": true
                },
                {
                  "label": "Vaginal Ovules",
                  "value": "Vaginal Ovules",
                  "is_final": true
                },
                {
                  "label": "Capsules",
                  "value": "Capsules",
                  "is_final": true
                },
                {
                  "label": "Vaginal Tablet",
                  "value": "Vaginal Tablet",
                  "is_final": true
                }
              ]
            }
          },
          {
            "label": "Vaginal Health",
            "value": "Vaginal Health",
            "next_step": {
              "step_id": "level_3",
              "question": "Do you prefer to use a vaginal gel?",
              "options": [
                {
                  "label": "Vaginal Gel",
                  "value": "Vaginal Gel",
                  "is_final": true
                }
              ]
            }
          },
          {
            "label": "Contraceptives",
            "value": "Contraceptives",
            "next_step": {
              "step_id": "level_3",
              "question": "Do you prefer to swallow your medicine?",
              "options": [
                {
                  "label": "Tablets",
                  "value": "Tablets",
                  "is_final": true
                }
              ]
            }
          }
        ]
      }
    }
  ]
}